crdb_fee_calculator-1.0.2.dist-info/licenses/LICENSE
crdbfee/__init__.py
crdbfee/calculator.py
crdb_fee_calculator-1.0.2.dist-info/METADATA
crdb_fee_calculator-1.0.2.dist-info/WHEEL
crdb_fee_calculator-1.0.2.dist-info/entry_points.txt
crdb_fee_calculator-1.0.2.dist-info/top_level.txt
crdb_fee_calculator-1.0.2.dist-info/RECORD
