Metadata-Version: 2.4
Name: crdb-fee-calculator
Version: 1.0.2
Summary: A command line tool for calculating fees and VAT from CRDB account statements in Excel format
Home-page: https://github.com/yourusername/crdb_fee_calculator
Author: Leon Kasdorf
Author-email: Leon Kasdorf <crdbfee@dropalias.com>
Maintainer-email: Leon Kasdorf <crdbfee@dropalias.com>
License: MIT
Project-URL: Homepage, https://github.com/yourusername/crdb_fee_calculator
Project-URL: Documentation, https://github.com/yourusername/crdb_fee_calculator#readme
Project-URL: Repository, https://github.com/yourusername/crdb_fee_calculator
Project-URL: Bug Tracker, https://github.com/yourusername/crdb_fee_calculator/issues
Keywords: crdb,fees,vat,excel,banking,tanzania,accounting
Classifier: Development Status :: 5 - Production/Stable
Classifier: Intended Audience :: Financial and Insurance Industry
Classifier: License :: OSI Approved :: MIT License
Classifier: Operating System :: OS Independent
Classifier: Programming Language :: Python :: 3
Classifier: Programming Language :: Python :: 3.7
Classifier: Programming Language :: Python :: 3.8
Classifier: Programming Language :: Python :: 3.9
Classifier: Programming Language :: Python :: 3.10
Classifier: Programming Language :: Python :: 3.11
Classifier: Programming Language :: Python :: 3.12
Classifier: Topic :: Office/Business :: Financial :: Accounting
Classifier: Topic :: Scientific/Engineering :: Information Analysis
Requires-Python: >=3.7
License-File: LICENSE
Requires-Dist: pandas>=1.5.0
Requires-Dist: openpyxl>=3.0.0
Requires-Dist: xlrd>=2.0.0
Provides-Extra: dev
Requires-Dist: pytest>=6.0; extra == "dev"
Requires-Dist: pytest-cov>=2.0; extra == "dev"
Requires-Dist: black>=21.0; extra == "dev"
Requires-Dist: flake8>=3.8; extra == "dev"
Requires-Dist: mypy>=0.800; extra == "dev"
Requires-Dist: twine>=3.0; extra == "dev"
Requires-Dist: build>=0.7; extra == "dev"
Dynamic: author
Dynamic: home-page
Dynamic: license-file
Dynamic: requires-python
